<?xml version="1.0" encoding="UTF-8" standalone="yes" ?>

<item>
<title> Search-Isi Atau Kulit </title>
<link>plugin://plugin.video.youtube/play/?video_id=HSotihcac5Y?list=RDHSotihcac5Y</link>
<thumbnail></thumbnail>
</item>

<item>
<title> Ukays-Disana Menanti Disini Menunggu </title>
<link>plugin://plugin.video.youtube/play/?video_id=s8scUNYSkCk?list=PL52Q9ucb_VTOb4gpQU78VGyMtfXXixoSb</link>
<thumbnail></thumbnail>
</item>

<item>
<title> Awie-Dipenjara Janji </title>
<link>plugin://plugin.video.youtube/play/?video_id=tbKmHjkr5Ds?list=PL52Q9ucb_VTOb4gpQU78VGyMtfXXixoSb</link>
<thumbnail></thumbnail>
</item>

<item>
<title> Mamat Exist-Rahsia Pohon Cemara </title>
<link>plugin://plugin.video.youtube/play/?video_id=mBsD64eNols?list=PLDEB238DEA431E7AE</link>
<thumbnail></thumbnail>
</item>

<item>
<title> Iklim-Mahligai Seribu Mimpi </title>
<link>plugin://plugin.video.youtube/play/?video_id=NhcR6sm-da8</link>
<thumbnail></thumbnail>
</item>

<item>
<title> Thomas-Bunga </title>
<link>plugin://plugin.video.youtube/play/?video_id=G02tdo9W2ew?list=PLmmlCnp5ho8T8mjSdjd3AyJ2SvuQ4qDs-</link>
<thumbnail></thumbnail>
</item>

<item>
<title> BPR-Seribu Tahun Takkan Mungkin </title>
<link>plugin://plugin.video.youtube/play/?video_id=nGyi-WSiO8M</link>
<thumbnail></thumbnail>
</item>













